dm_platform_utils/DataLoader.py
dm_platform_utils/DataWriter.py
dm_platform_utils/__init__.py
dm_platform_utils/utils.py
dm_platform_utils/conf/process_dtypes.yml
dm_platform_utils/conf/raw_sql.yml
dm_platform_utils/conf/sql.yml
dm_platform_utils-1.3.12.dist-info/LICENSE.md
dm_platform_utils-1.3.12.dist-info/METADATA
dm_platform_utils-1.3.12.dist-info/WHEEL
dm_platform_utils-1.3.12.dist-info/top_level.txt
dm_platform_utils-1.3.12.dist-info/RECORD
