Metadata-Version: 2.1
Name: dm-platform-utils
Version: 1.3.12
Summary: Data mining platform develop utils
Home-page: http://gitlab.admin.bluemoon.com.cn/DM_group/dm-platform-utils.git
Author: Shenxian Shi
Author-email: shishenxian@bluemoon.com.cn
License: MIT License        
Platform: UNKNOWN
Requires-Python: >=3.6
License-File: LICENSE.md
Requires-Dist: bmai-dm-hbase (>=0.2.1)
Requires-Dist: dm-easy-db (>=0.1.1)
Requires-Dist: requests (>=2.28.1)
